setup.py
distributions_adeola/Binomialdistribution.py
distributions_adeola/Gaussiandistribution.py
distributions_adeola/Generaldistribution.py
distributions_adeola/__init__.py
distributions_adeola.egg-info/PKG-INFO
distributions_adeola.egg-info/SOURCES.txt
distributions_adeola.egg-info/dependency_links.txt
distributions_adeola.egg-info/not-zip-safe
distributions_adeola.egg-info/top_level.txt